elabapy/Manager.py
elabapy/__init__.py
elabapy/baseapi.py
elabapy-1.1.0.dist-info/LICENCE
elabapy-1.1.0.dist-info/METADATA
elabapy-1.1.0.dist-info/WHEEL
elabapy-1.1.0.dist-info/top_level.txt
elabapy-1.1.0.dist-info/RECORD
