Metadata-Version: 2.1
Name: elabapy
Version: 1.1.0
Summary: elabftw API to manage experiments and items
Home-page: https://github.com/elabftw/elabapy
Author: Nicolas CARPi
Author-email: nico-git@deltablot.email
License: GPL v3
License-File: LICENCE
Requires-Dist: requests
